pydictcc/__init__.py
pydictcc/builder.py
pydictcc/dbm_dictionary.py
pydictcc/entities.py
pydictcc/main.py
pydictcc/presenter.py
pydictcc/translator.py
pydictcc-0.1.0.dist-info/METADATA
pydictcc-0.1.0.dist-info/WHEEL
pydictcc-0.1.0.dist-info/entry_points.txt
pydictcc-0.1.0.dist-info/RECORD
