Metadata-Version: 2.1
Name: pydictcc
Version: 0.1.0
Summary: 
License: GPL v3
Keywords: dictionary
Author: Tobias Witt
Author-email: sleepywitti@gmail.com
Requires-Python: >=3.10,<4.0
Classifier: License :: OSI Approved :: GNU General Public License v3 (GPLv3)
Classifier: License :: Other/Proprietary License
Classifier: Programming Language :: Python :: 3
Classifier: Programming Language :: Python :: 3.10
Classifier: Programming Language :: Python :: 3.11
Classifier: Programming Language :: Python :: 3.12
Classifier: Programming Language :: Python :: 3 :: Only
Classifier: Topic :: Education
Classifier: Topic :: Office/Business
Classifier: Topic :: Software Development :: Build Tools
Classifier: Topic :: Software Development :: Libraries :: Python Modules
Classifier: Topic :: Utilities
Provides-Extra: progressbar
Requires-Dist: tqdm (>=4.66.6,<5.0.0) ; extra == "progressbar"
